awslabs/__init__.py
awslabs/aws_serverless_mcp_server/__init__.py
awslabs/aws_serverless_mcp_server/models.py
awslabs/aws_serverless_mcp_server/server.py
awslabs/aws_serverless_mcp_server/resources/__init__.py
awslabs/aws_serverless_mcp_server/resources/deployment_details.py
awslabs/aws_serverless_mcp_server/resources/deployment_list.py
awslabs/aws_serverless_mcp_server/resources/template_details.py
awslabs/aws_serverless_mcp_server/resources/template_list.py
awslabs/aws_serverless_mcp_server/template/__init__.py
awslabs/aws_serverless_mcp_server/template/registry.py
awslabs/aws_serverless_mcp_server/template/renderer.py
awslabs/aws_serverless_mcp_server/template/templates/README.md
awslabs/aws_serverless_mcp_server/template/templates/backend.j2
awslabs/aws_serverless_mcp_server/template/templates/frontend.j2
awslabs/aws_serverless_mcp_server/template/templates/fullstack.j2
awslabs/aws_serverless_mcp_server/templates/__init__.py
awslabs/aws_serverless_mcp_server/templates/iam_policies.py
awslabs/aws_serverless_mcp_server/tools/common/base_tool.py
awslabs/aws_serverless_mcp_server/tools/esm/__init__.py
awslabs/aws_serverless_mcp_server/tools/esm/esm_diagnosis.py
awslabs/aws_serverless_mcp_server/tools/esm/esm_guidance.py
awslabs/aws_serverless_mcp_server/tools/esm/esm_recommend.py
awslabs/aws_serverless_mcp_server/tools/esm/secure_esm_guidance.py
awslabs/aws_serverless_mcp_server/tools/guidance/__init__.py
awslabs/aws_serverless_mcp_server/tools/guidance/deploy_serverless_app_help.py
awslabs/aws_serverless_mcp_server/tools/guidance/get_iac_guidance.py
awslabs/aws_serverless_mcp_server/tools/guidance/get_lambda_event_schemas.py
awslabs/aws_serverless_mcp_server/tools/guidance/get_lambda_guidance.py
awslabs/aws_serverless_mcp_server/tools/guidance/get_serverless_templates.py
awslabs/aws_serverless_mcp_server/tools/poller/__init__.py
awslabs/aws_serverless_mcp_server/tools/poller/esm_diagnosis.py
awslabs/aws_serverless_mcp_server/tools/poller/esm_guidance.py
awslabs_aws_serverless_mcp_server-0.1.15.dist-info/METADATA
awslabs_aws_serverless_mcp_server-0.1.15.dist-info/WHEEL
awslabs_aws_serverless_mcp_server-0.1.15.dist-info/entry_points.txt
awslabs_aws_serverless_mcp_server-0.1.15.dist-info/RECORD
